py_cep_search/__init__.py
py_cep_search/cepsearch.py
py_cep_search/response_correios.py
py_cep_search/version.py
PyCEPSearch-0.0.1.dist-info/LICENSE
PyCEPSearch-0.0.1.dist-info/METADATA
PyCEPSearch-0.0.1.dist-info/WHEEL
PyCEPSearch-0.0.1.dist-info/top_level.txt
PyCEPSearch-0.0.1.dist-info/RECORD
