Metadata-Version: 2.1
Name: PyCEPSearch
Version: 0.0.1
Summary: A package helps you to get a CEP or Address from brazilian's postal service.
Author-email: Joao Paulo de Castro Lima <joao@paulo.com>
Project-URL: Homepage, https://github.com/joao2391/pycepsearch
Project-URL: Issues, https://github.com/joao2391/pycepsearch/issues
Classifier: Programming Language :: Python :: 3
Classifier: License :: OSI Approved :: MIT License
Classifier: Operating System :: OS Independent
Requires-Python: >=3.8
License-File: LICENSE
